<?xml version = '1.0' encoding = 'UTF-8'?>
<Relation class="oracle.dbtools.crest.model.design.logical.Relation" name="Relation_260" id="CDDFB728-9FA4-B57E-DCB0-4524C7153559" directorySegmentName="seg_0">
<createdBy>kopasiak</createdBy>
<createdTime>2013-01-31 22:08:02 UTC</createdTime>
<ownerDesignName>bd2</ownerDesignName>
<engineerTo>
<item key="42B1583A-24C2-0CE7-F29F-1BAC13535EBF" value="true"/>
</engineerTo>
<identifying>false</identifying>
<optionalSource>true</optionalSource>
<optionalTarget>true</optionalTarget>
<sourceCardinality>1</sourceCardinality>
<sourceEntity>F95AF667-67E2-1DE6-BCEE-26D551509D1D</sourceEntity>
<targetCardinalityString>*</targetCardinalityString>
<targetEntity>F15E844A-2433-49EA-D7EB-40F1DACF5928</targetEntity>
<transferable>true</transferable>
</Relation>